[
  {
    "full_name": "Ocraniawan/Food_Delivery_API",
    "stargazers_count": 3,
    "open_issues_count": 4,
    "forks_count": 2
  },
  {
    "full_name": "MunGell/awesome-for-beginners",
    "stargazers_count": 45374,
    "open_issues_count": 80,
    "forks_count": 6035
  },
  {
    "full_name": "ignacio-chiazzo/Algorithms-Leetcode-Javascript",
    "stargazers_count": 357,
    "open_issues_count": 4,
    "forks_count": 68
  },
  {
    "full_name": "Your-First-Open-Source-Project/Your-First-Open-Source-Project",
    "stargazers_count": 75,
    "open_issues_count": 1,
    "forks_count": 76
  },
  {
    "full_name": "blossom-babs/Data-structures-and-algorithm",
    "stargazers_count": 11,
    "open_issues_count": 1,
    "forks_count": 5
  },
  {
    "full_name": "deepsourcelabs/good-first-issue",
    "stargazers_count": 1370,
    "open_issues_count": 65,
    "forks_count": 390
  },
  {
    "full_name": "aviyelverse/aviyel-first-pr",
    "stargazers_count": 20,
    "open_issues_count": 3,
    "forks_count": 70
  },
  {
    "full_name": "saadpasta/developerFolio",
    "stargazers_count": 3625,
    "open_issues_count": 20,
    "forks_count": 1645
  },
  {
    "full_name": "john-smilga/node-express-course",
    "stargazers_count": 2055,
    "open_issues_count": 12,
    "forks_count": 2090
  },
  {
    "full_name": "tapaswenipathak/Open-Source-Programs",
    "stargazers_count": 2995,
    "open_issues_count": 28,
    "forks_count": 711
  },
  {
    "full_name": "airbnb/javascript",
    "stargazers_count": 128402,
    "open_issues_count": 149,
    "forks_count": 24480
  }
]