[
  {
    "full_name": "Gunji-ng/coin-wallet-api",
    "stargazers_count": 2,
    "open_issues_count": 0,
    "forks_count": 0
  },
  {
    "full_name": "novuhq/novu",
    "stargazers_count": 35919,
    "open_issues_count": 263,
    "forks_count": 3943
  },
  {
    "full_name": "adam-p/markdown-here",
    "stargazers_count": 59724,
    "open_issues_count": 319,
    "forks_count": 11241
  },
  {
    "full_name": "Ocraniawan/Food_Delivery_API",
    "stargazers_count": 4,
    "open_issues_count": 7,
    "forks_count": 2
  },
  {
    "full_name": "MunGell/awesome-for-beginners",
    "stargazers_count": 70367,
    "open_issues_count": 6,
    "forks_count": 7051
  },
  {
    "full_name": "ignacio-chiazzo/Algorithms-Leetcode-Javascript",
    "stargazers_count": 630,
    "open_issues_count": 8,
    "forks_count": 91
  },
  {
    "full_name": "yfosp/start-here",
    "stargazers_count": 236,
    "open_issues_count": 1,
    "forks_count": 288
  },
  {
    "full_name": "blossom-babs/Data-structures-and-algorithm",
    "stargazers_count": 12,
    "open_issues_count": 1,
    "forks_count": 5
  },
  {
    "full_name": "DeepSourceCorp/good-first-issue",
    "stargazers_count": 2564,
    "open_issues_count": 226,
    "forks_count": 795
  },
  {
    "full_name": "aviyelverse/aviyel-first-pr",
    "stargazers_count": 20,
    "open_issues_count": 6,
    "forks_count": 59
  },
  {
    "full_name": "saadpasta/developerFolio",
    "stargazers_count": 5635,
    "open_issues_count": 102,
    "forks_count": 2923
  },
  {
    "full_name": "john-smilga/node-express-course",
    "stargazers_count": 3646,
    "open_issues_count": 29,
    "forks_count": 3826
  },
  {
    "full_name": "tapaswenipathak/Open-Source-Programs",
    "stargazers_count": 3710,
    "open_issues_count": 39,
    "forks_count": 794
  },
  {
    "full_name": "airbnb/javascript",
    "stargazers_count": 145719,
    "open_issues_count": 166,
    "forks_count": 26559
  }
]